changelog/README.rst
docs/Makefile
docs/make.bat
docs/requirements.txt
docs/source/api.rst
docs/source/calibration.rst
docs/source/catalog.rst
docs/source/changelog.rst
docs/source/citation.rst
docs/source/conf.py
docs/source/develop.rst
docs/source/getting_started.rst
docs/source/index.rst
docs/source/utilities.rst
docs/source/_templates/autosummary/custom-module-template.rst
docs/source/_templates/autosummary/module.rst
docs/source/venv/bin/rst2html.py
docs/source/venv/bin/rst2html4.py
docs/source/venv/bin/rst2html5.py
docs/source/venv/bin/rst2latex.py
docs/source/venv/bin/rst2man.py
docs/source/venv/bin/rst2odt.py
docs/source/venv/bin/rst2odt_prepstyles.py
docs/source/venv/bin/rst2pseudoxml.py
docs/source/venv/bin/rst2s5.py
docs/source/venv/bin/rst2xetex.py
docs/source/venv/bin/rst2xml.py
docs/source/venv/bin/rstpep2html.py
examples/README.md
sospice/CITATION.rst
sospice/__init__.py
sospice/_version.py
sospice/calibrate/__init__.py
sospice/calibrate/uncertainties.py
sospice/calibrate/tests/__init__.py
sospice/calibrate/tests/test_uncertainties.py
sospice/catalog/__init__.py
sospice/catalog/catalog.py
sospice/catalog/file_metadata.py
sospice/catalog/release.py
sospice/catalog/tests/__init__.py
sospice/catalog/tests/test_catalog.py
sospice/catalog/tests/test_file_metadata.py
sospice/catalog/tests/test_release.py
sospice/data/__init__.py
sospice/data/calibration/effective_area.sav
sospice/data/tests/__init__.py
sospice/instrument_modelling/__init__.py
sospice/instrument_modelling/observation.py
sospice/instrument_modelling/spice.py
sospice/instrument_modelling/study.py
sospice/instrument_modelling/tests/__init__.py
sospice/instrument_modelling/tests/test_observation.py
sospice/instrument_modelling/tests/test_spice.py
sospice/instrument_modelling/tests/test_study.py
sospice/psf/__init__.py
sospice/psf/tests/__init__.py
sospice/tests/__init__.py
sospice/util/__init__.py
sospice/util/fov.py
sospice/util/rss.py
sospice/util/sigma_clipping.py
sospice-0.0.8.dist-info/LICENSE
sospice-0.0.8.dist-info/METADATA
sospice-0.0.8.dist-info/WHEEL
sospice-0.0.8.dist-info/top_level.txt
sospice-0.0.8.dist-info/RECORD
